chancery/.testapi.py.swp
chancery/__init__.py
chancery/chancery.py
chancery/needler.py
chancery/testapi.py
chancery-0.9.6.dist-info/entry_points.txt
chancery-0.9.6.dist-info/WHEEL
chancery-0.9.6.dist-info/METADATA
chancery-0.9.6.dist-info/RECORD
