Metadata-Version: 2.1
Name: chancery
Version: 0.9.6
Summary: Chancery is a simple text editor with predefined openQA snippets.
License: GPL-3.0-or-later
Author: Lukáš Růžička
Author-email: lruzicka@redhat.com
Requires-Python: >=3.10,<4.0
Classifier: License :: OSI Approved :: GNU General Public License v3 or later (GPLv3+)
Classifier: Programming Language :: Python :: 3
Classifier: Programming Language :: Python :: 3.10
Requires-Dist: needly (>=2.5.61,<3.0.0)
